generateweather/__init__.py
generateweather/generateweather.py
generateweather-1.1.dist-info/METADATA
generateweather-1.1.dist-info/WHEEL
generateweather-1.1.dist-info/top_level.txt
generateweather-1.1.dist-info/RECORD
