Metadata-Version: 2.4
Name: generateweather
Version: 1.1
Summary: A random weather generator
Author: holodosik
Project-URL: Homepage, https://github.com/holodosik
Classifier: License :: OSI Approved :: MIT License
Classifier: Programming Language :: Python :: 3
Classifier: Operating System :: OS Independent
